[
  {
    "LiveFrom": "01/01/2017",
    "ID": "AllocationProposalList",
    "ListElementCode": "Circuit judge",
    "ListElement": "Circuit Judge",
    "DisplayOrder": 1
  },
  {
    "LiveFrom": "01/01/2017",
    "ID": "AllocationProposalList",
    "ListElementCode": "Section 9 circuit judge",
    "ListElement": "Circuit Judge (Section 9)",
    "DisplayOrder": 2
  },
  {
    "LiveFrom": "01/01/2017",
    "ID": "AllocationProposalList",
    "ListElementCode": "District judge",
    "ListElement": "District Judge",
    "DisplayOrder": 3
  },
  {
    "LiveFrom": "01/01/2017",
    "ID": "AllocationProposalList",
    "ListElementCode": "Lay justices",
    "ListElement": "Magistrate",
    "DisplayOrder": 4
  },
  {
    "LiveFrom": "01/01/2017",
    "ID": "AllocationProposalList",
    "ListElementCode": "High Court judge",
    "ListElement": "High Court Judge",
    "DisplayOrder": 5
  }
]
