[
  {
    "LiveFrom": "01/01/2017",
    "ID": "AllocationProposal",
    "CaseEventID": "otherProposal",
    "CaseFieldID": "allocationProposal",
    "ListElementCode": "proposalV2",
    "EventElementLabel": "Which level of judge do you recommend for this case?",
    "FieldDisplayOrder": 1,
    "DisplayContext": "MANDATORY"
  },
  {
    "LiveFrom": "01/01/2017",
    "ID": "AllocationProposal",
    "CaseEventID": "otherProposal",
    "CaseFieldID": "allocationProposal",
    "ListElementCode": "reasonLabel1",
    "EventElementLabel": "Give case specific reasons for your recommendation, including details of any previous proceedings. You should refer to the [President's Guidance](https://www.judiciary.uk/wp-content/uploads/2013/03/President%E2%80%99s-Guidance-on-Allocation-and-Gatekeeping.pdf) and to the [schedule](https://www.judiciary.uk/wp-content/uploads/2013/03/Schedule-to-the-President%E2%80%99s-Guidance-on-Allocation-and-Gatekeeping.pdf). This will help the court appoint an appropriate judge to the case.",
    "FieldDisplayOrder": 2,
    "DisplayContext": "READONLY"
  },
  {
    "LiveFrom": "01/01/2017",
    "ID": "AllocationProposal",
    "CaseEventID": "otherProposal",
    "CaseFieldID": "allocationProposal",
    "ListElementCode": "proposalReason",
    "FieldDisplayOrder": 3,
    "DisplayContext": "MANDATORY"
  }
]
