[
  {
    "LiveFrom": "01/01/2017",
    "CaseTypeID": "CARE_SUPERVISION_EPO",
    "CaseFieldID": "additionalApplicationsBundle",
    "ListElementCode": "c2DocumentBundle",
    "AccessControl": [
      {
        "UserRoles": [
          "[CAFCASSSOLICITOR]",
          "caseworker-publiclaw-cafcass",
          "caseworker-publiclaw-courtadmin",
          "caseworker-publiclaw-systemupdate",
          "[EPSMANAGING]",
          "[LABARRISTER]",
          "[LAMANAGING]",
          "[LASOLICITOR]",
          "[SOLICITOR]",
          "[SOLICITORA]",
          "[SOLICITORB]",
          "[SOLICITORC]",
          "[SOLICITORD]",
          "[SOLICITORE]",
          "[SOLICITORF]",
          "[SOLICITORG]",
          "[SOLICITORH]",
          "[SOLICITORI]",
          "[SOLICITORJ]",
          "[CHILDSOLICITORA]",
          "[CHILDSOLICITORB]",
          "[CHILDSOLICITORC]",
          "[CHILDSOLICITORD]",
          "[CHILDSOLICITORE]",
          "[CHILDSOLICITORF]",
          "[CHILDSOLICITORG]",
          "[CHILDSOLICITORH]",
          "[CHILDSOLICITORI]",
          "[CHILDSOLICITORJ]",
          "[CHILDSOLICITORK]",
          "[CHILDSOLICITORL]",
          "[CHILDSOLICITORM]",
          "[CHILDSOLICITORN]",
          "[CHILDSOLICITORO]"
        ],
        "CRUD": "CRU"
      },
      {
        "UserRoles": [
          "[BARRISTER]",
          "caseworker-publiclaw-gatekeeper",
          "caseworker-publiclaw-judiciary",
          "caseworker-publiclaw-magistrate"
        ],
        "CRUD": "RU"
      }
    ]
  },
  {
    "LiveFrom": "01/01/2017",
    "CaseTypeID": "CARE_SUPERVISION_EPO",
    "CaseFieldID": "additionalApplicationsBundle",
    "ListElementCode": "otherApplicationsBundle",
    "AccessControl": [
      {
        "UserRoles": [
          "[CAFCASSSOLICITOR]",
          "caseworker-publiclaw-cafcass",
          "caseworker-publiclaw-courtadmin",
          "caseworker-publiclaw-systemupdate",
          "[EPSMANAGING]",
          "[LABARRISTER]",
          "[LAMANAGING]",
          "[LASOLICITOR]",
          "[SOLICITOR]",
          "[SOLICITORA]",
          "[SOLICITORB]",
          "[SOLICITORC]",
          "[SOLICITORD]",
          "[SOLICITORE]",
          "[SOLICITORF]",
          "[SOLICITORG]",
          "[SOLICITORH]",
          "[SOLICITORI]",
          "[SOLICITORJ]",
          "[CHILDSOLICITORA]",
          "[CHILDSOLICITORB]",
          "[CHILDSOLICITORC]",
          "[CHILDSOLICITORD]",
          "[CHILDSOLICITORE]",
          "[CHILDSOLICITORF]",
          "[CHILDSOLICITORG]",
          "[CHILDSOLICITORH]",
          "[CHILDSOLICITORI]",
          "[CHILDSOLICITORJ]",
          "[CHILDSOLICITORK]",
          "[CHILDSOLICITORL]",
          "[CHILDSOLICITORM]",
          "[CHILDSOLICITORN]",
          "[CHILDSOLICITORO]"
        ],
        "CRUD": "CRU"
      },
      {
        "UserRoles": [
          "[BARRISTER]",
          "caseworker-publiclaw-gatekeeper",
          "caseworker-publiclaw-judiciary",
          "caseworker-publiclaw-magistrate"
        ],
        "CRUD": "RU"
      }
    ]
  },
  {
    "LiveFrom": "01/01/2017",
    "CaseTypeID": "CARE_SUPERVISION_EPO",
    "CaseFieldID": "additionalApplicationsBundle",
    "ListElementCode": "pbaPayment",
    "AccessControl": [
      {
        "UserRoles": [
          "[CAFCASSSOLICITOR]",
          "caseworker-publiclaw-cafcass",
          "caseworker-publiclaw-courtadmin",
          "caseworker-publiclaw-systemupdate",
          "[EPSMANAGING]",
          "[LABARRISTER]",
          "[LAMANAGING]",
          "[LASOLICITOR]",
          "[SOLICITOR]",
          "[SOLICITORA]",
          "[SOLICITORB]",
          "[SOLICITORC]",
          "[SOLICITORD]",
          "[SOLICITORE]",
          "[SOLICITORF]",
          "[SOLICITORG]",
          "[SOLICITORH]",
          "[SOLICITORI]",
          "[SOLICITORJ]",
          "[CHILDSOLICITORA]",
          "[CHILDSOLICITORB]",
          "[CHILDSOLICITORC]",
          "[CHILDSOLICITORD]",
          "[CHILDSOLICITORE]",
          "[CHILDSOLICITORF]",
          "[CHILDSOLICITORG]",
          "[CHILDSOLICITORH]",
          "[CHILDSOLICITORI]",
          "[CHILDSOLICITORJ]",
          "[CHILDSOLICITORK]",
          "[CHILDSOLICITORL]",
          "[CHILDSOLICITORM]",
          "[CHILDSOLICITORN]",
          "[CHILDSOLICITORO]"
        ],
        "CRUD": "CRU"
      },
      {
        "UserRoles": [
          "[BARRISTER]",
          "caseworker-publiclaw-gatekeeper",
          "caseworker-publiclaw-judiciary",
          "caseworker-publiclaw-magistrate"
        ],
        "CRUD": "RU"
      }
    ]
  },
  {
    "LiveFrom": "01/01/2017",
    "CaseTypeID": "CARE_SUPERVISION_EPO",
    "CaseFieldID": "additionalApplicationsBundle",
    "ListElementCode": "uploadedDateTime",
    "AccessControl": [
      {
        "UserRoles": [
          "[LABARRISTER]",
          "[SOLICITOR]",
          "[SOLICITORA]",
          "[SOLICITORB]",
          "[SOLICITORC]",
          "[SOLICITORD]",
          "[SOLICITORE]",
          "[SOLICITORF]",
          "[SOLICITORG]",
          "[SOLICITORH]",
          "[SOLICITORI]",
          "[SOLICITORJ]",
          "[CHILDSOLICITORA]",
          "[CHILDSOLICITORB]",
          "[CHILDSOLICITORC]",
          "[CHILDSOLICITORD]",
          "[CHILDSOLICITORE]",
          "[CHILDSOLICITORF]",
          "[CHILDSOLICITORG]",
          "[CHILDSOLICITORH]",
          "[CHILDSOLICITORI]",
          "[CHILDSOLICITORJ]",
          "[CHILDSOLICITORK]",
          "[CHILDSOLICITORL]",
          "[CHILDSOLICITORM]",
          "[CHILDSOLICITORN]",
          "[CHILDSOLICITORO]",
          "[LASOLICITOR]",
          "[CAFCASSSOLICITOR]",
          "caseworker-publiclaw-courtadmin",
          "caseworker-publiclaw-cafcass"
        ],
        "CRUD": "CRU"
      },
      {
        "UserRoles": [
          "caseworker-publiclaw-gatekeeper",
          "caseworker-publiclaw-judiciary",
          "caseworker-publiclaw-magistrate",
          "[BARRISTER]"
        ],
        "CRUD": "R"
      }
    ]
  },
  {
    "LiveFrom": "01/01/2017",
    "CaseTypeID": "CARE_SUPERVISION_EPO",
    "CaseFieldID": "additionalApplicationsBundle",
    "ListElementCode": "author",
    "AccessControl": [
      {
        "UserRoles": [
          "[LABARRISTER]",
          "[SOLICITOR]",
          "[SOLICITORA]",
          "[SOLICITORB]",
          "[SOLICITORC]",
          "[SOLICITORD]",
          "[SOLICITORE]",
          "[SOLICITORF]",
          "[SOLICITORG]",
          "[SOLICITORH]",
          "[SOLICITORI]",
          "[SOLICITORJ]",
          "[CHILDSOLICITORA]",
          "[CHILDSOLICITORB]",
          "[CHILDSOLICITORC]",
          "[CHILDSOLICITORD]",
          "[CHILDSOLICITORE]",
          "[CHILDSOLICITORF]",
          "[CHILDSOLICITORG]",
          "[CHILDSOLICITORH]",
          "[CHILDSOLICITORI]",
          "[CHILDSOLICITORJ]",
          "[CHILDSOLICITORK]",
          "[CHILDSOLICITORL]",
          "[CHILDSOLICITORM]",
          "[CHILDSOLICITORN]",
          "[CHILDSOLICITORO]",
          "[LASOLICITOR]",
          "[CAFCASSSOLICITOR]",
          "caseworker-publiclaw-courtadmin",
          "caseworker-publiclaw-cafcass"
        ],
        "CRUD": "CRU"
      },
      {
        "UserRoles": [
          "caseworker-publiclaw-gatekeeper",
          "caseworker-publiclaw-judiciary",
          "caseworker-publiclaw-magistrate",
          "[BARRISTER]"
        ],
        "CRUD": "R"
      }
    ]
  },
  {
    "LiveFrom": "01/01/2017",
    "CaseTypeID": "CARE_SUPERVISION_EPO",
    "CaseFieldID": "additionalApplicationsBundle",
    "ListElementCode": "c2DocumentBundle.applicantName",
    "AccessControl": [
      {
        "UserRoles": [
          "[LABARRISTER]",
          "[SOLICITOR]",
          "[SOLICITORA]",
          "[SOLICITORB]",
          "[SOLICITORC]",
          "[SOLICITORD]",
          "[SOLICITORE]",
          "[SOLICITORF]",
          "[SOLICITORG]",
          "[SOLICITORH]",
          "[SOLICITORI]",
          "[SOLICITORJ]",
          "[CHILDSOLICITORA]",
          "[CHILDSOLICITORB]",
          "[CHILDSOLICITORC]",
          "[CHILDSOLICITORD]",
          "[CHILDSOLICITORE]",
          "[CHILDSOLICITORF]",
          "[CHILDSOLICITORG]",
          "[CHILDSOLICITORH]",
          "[CHILDSOLICITORI]",
          "[CHILDSOLICITORJ]",
          "[CHILDSOLICITORK]",
          "[CHILDSOLICITORL]",
          "[CHILDSOLICITORM]",
          "[CHILDSOLICITORN]",
          "[CHILDSOLICITORO]",
          "[LASOLICITOR]",
          "[CAFCASSSOLICITOR]",
          "caseworker-publiclaw-courtadmin",
          "caseworker-publiclaw-cafcass"
        ],
        "CRUD": "CRU"
      },
      {
        "UserRoles": [
          "caseworker-publiclaw-gatekeeper",
          "caseworker-publiclaw-judiciary",
          "caseworker-publiclaw-magistrate",
          "[BARRISTER]"
        ],
        "CRUD": "R"
      }
    ]
  },
  {
    "LiveFrom": "01/01/2017",
    "CaseTypeID": "CARE_SUPERVISION_EPO",
    "CaseFieldID": "additionalApplicationsBundle",
    "ListElementCode": "c2DocumentBundle.document",
    "AccessControl": [
      {
        "UserRoles": [
          "[LABARRISTER]",
          "[SOLICITOR]",
          "[SOLICITORA]",
          "[SOLICITORB]",
          "[SOLICITORC]",
          "[SOLICITORD]",
          "[SOLICITORE]",
          "[SOLICITORF]",
          "[SOLICITORG]",
          "[SOLICITORH]",
          "[SOLICITORI]",
          "[SOLICITORJ]",
          "[CHILDSOLICITORA]",
          "[CHILDSOLICITORB]",
          "[CHILDSOLICITORC]",
          "[CHILDSOLICITORD]",
          "[CHILDSOLICITORE]",
          "[CHILDSOLICITORF]",
          "[CHILDSOLICITORG]",
          "[CHILDSOLICITORH]",
          "[CHILDSOLICITORI]",
          "[CHILDSOLICITORJ]",
          "[CHILDSOLICITORK]",
          "[CHILDSOLICITORL]",
          "[CHILDSOLICITORM]",
          "[CHILDSOLICITORN]",
          "[CHILDSOLICITORO]",
          "[LASOLICITOR]",
          "[CAFCASSSOLICITOR]",
          "caseworker-publiclaw-courtadmin",
          "caseworker-publiclaw-cafcass"
        ],
        "CRUD": "CRU"
      },
      {
        "UserRoles": [
          "caseworker-publiclaw-gatekeeper",
          "caseworker-publiclaw-judiciary",
          "caseworker-publiclaw-magistrate",
          "[BARRISTER]"
        ],
        "CRUD": "R"
      }
    ]
  },
  {
    "LiveFrom": "01/01/2017",
    "CaseTypeID": "CARE_SUPERVISION_EPO",
    "CaseFieldID": "additionalApplicationsBundle",
    "ListElementCode": "c2DocumentBundle.type",
    "AccessControl": [
      {
        "UserRoles": [
          "[LABARRISTER]",
          "[SOLICITOR]",
          "[SOLICITORA]",
          "[SOLICITORB]",
          "[SOLICITORC]",
          "[SOLICITORD]",
          "[SOLICITORE]",
          "[SOLICITORF]",
          "[SOLICITORG]",
          "[SOLICITORH]",
          "[SOLICITORI]",
          "[SOLICITORJ]",
          "[CHILDSOLICITORA]",
          "[CHILDSOLICITORB]",
          "[CHILDSOLICITORC]",
          "[CHILDSOLICITORD]",
          "[CHILDSOLICITORE]",
          "[CHILDSOLICITORF]",
          "[CHILDSOLICITORG]",
          "[CHILDSOLICITORH]",
          "[CHILDSOLICITORI]",
          "[CHILDSOLICITORJ]",
          "[CHILDSOLICITORK]",
          "[CHILDSOLICITORL]",
          "[CHILDSOLICITORM]",
          "[CHILDSOLICITORN]",
          "[CHILDSOLICITORO]",
          "[LASOLICITOR]",
          "[CAFCASSSOLICITOR]",
          "caseworker-publiclaw-courtadmin",
          "caseworker-publiclaw-cafcass"
        ],
        "CRUD": "CRU"
      },
      {
        "UserRoles": [
          "caseworker-publiclaw-gatekeeper",
          "caseworker-publiclaw-judiciary",
          "caseworker-publiclaw-magistrate",
          "[BARRISTER]"
        ],
        "CRUD": "R"
      }
    ]
  },
  {
    "LiveFrom": "01/01/2017",
    "CaseTypeID": "CARE_SUPERVISION_EPO",
    "CaseFieldID": "additionalApplicationsBundle",
    "ListElementCode": "c2DocumentBundle.uploadedDateTime",
    "AccessControl": [
      {
        "UserRoles": [
          "[LABARRISTER]",
          "[SOLICITOR]",
          "[SOLICITORA]",
          "[SOLICITORB]",
          "[SOLICITORC]",
          "[SOLICITORD]",
          "[SOLICITORE]",
          "[SOLICITORF]",
          "[SOLICITORG]",
          "[SOLICITORH]",
          "[SOLICITORI]",
          "[SOLICITORJ]",
          "[CHILDSOLICITORA]",
          "[CHILDSOLICITORB]",
          "[CHILDSOLICITORC]",
          "[CHILDSOLICITORD]",
          "[CHILDSOLICITORE]",
          "[CHILDSOLICITORF]",
          "[CHILDSOLICITORG]",
          "[CHILDSOLICITORH]",
          "[CHILDSOLICITORI]",
          "[CHILDSOLICITORJ]",
          "[CHILDSOLICITORK]",
          "[CHILDSOLICITORL]",
          "[CHILDSOLICITORM]",
          "[CHILDSOLICITORN]",
          "[CHILDSOLICITORO]",
          "[LASOLICITOR]",
          "[CAFCASSSOLICITOR]",
          "caseworker-publiclaw-courtadmin",
          "caseworker-publiclaw-cafcass"
        ],
        "CRUD": "CRU"
      },
      {
        "UserRoles": [
          "caseworker-publiclaw-gatekeeper",
          "caseworker-publiclaw-judiciary",
          "caseworker-publiclaw-magistrate",
          "[BARRISTER]"
        ],
        "CRUD": "R"
      }
    ]
  },
  {
    "LiveFrom": "01/01/2017",
    "CaseTypeID": "CARE_SUPERVISION_EPO",
    "CaseFieldID": "additionalApplicationsBundle",
    "ListElementCode": "c2DocumentBundle.author",
    "AccessControl": [
      {
        "UserRoles": [
          "[LABARRISTER]",
          "[SOLICITOR]",
          "[SOLICITORA]",
          "[SOLICITORB]",
          "[SOLICITORC]",
          "[SOLICITORD]",
          "[SOLICITORE]",
          "[SOLICITORF]",
          "[SOLICITORG]",
          "[SOLICITORH]",
          "[SOLICITORI]",
          "[SOLICITORJ]",
          "[CHILDSOLICITORA]",
          "[CHILDSOLICITORB]",
          "[CHILDSOLICITORC]",
          "[CHILDSOLICITORD]",
          "[CHILDSOLICITORE]",
          "[CHILDSOLICITORF]",
          "[CHILDSOLICITORG]",
          "[CHILDSOLICITORH]",
          "[CHILDSOLICITORI]",
          "[CHILDSOLICITORJ]",
          "[CHILDSOLICITORK]",
          "[CHILDSOLICITORL]",
          "[CHILDSOLICITORM]",
          "[CHILDSOLICITORN]",
          "[CHILDSOLICITORO]",
          "[LASOLICITOR]",
          "[CAFCASSSOLICITOR]",
          "caseworker-publiclaw-courtadmin",
          "caseworker-publiclaw-cafcass"
        ],
        "CRUD": "CRU"
      },
      {
        "UserRoles": [
          "caseworker-publiclaw-gatekeeper",
          "caseworker-publiclaw-judiciary",
          "caseworker-publiclaw-magistrate",
          "[BARRISTER]"
        ],
        "CRUD": "R"
      }
    ]
  },
  {
    "LiveFrom": "01/01/2017",
    "CaseTypeID": "CARE_SUPERVISION_EPO",
    "CaseFieldID": "additionalApplicationsBundle",
    "ListElementCode": "c2DocumentBundle.supportingEvidenceBundle",
    "AccessControl": [
      {
        "UserRoles": [
          "caseworker-publiclaw-courtadmin"
        ],
        "CRUD": "CRU"
      },
      {
        "UserRoles": [
          "[LASOLICITOR]",
          "[LABARRISTER]",
          "[CAFCASSSOLICITOR]",
          "[SOLICITOR]"
        ],
        "CRUD": "CU"
      },
      {
        "UserRoles": [
          "caseworker-publiclaw-gatekeeper",
          "caseworker-publiclaw-judiciary",
          "caseworker-publiclaw-magistrate"
        ],
        "CRUD": "R"
      },
      {
        "UserRoles": [
          "[BARRISTER]",
          "caseworker-publiclaw-cafcass"
        ],
        "CRUD": "U"
      }
    ]
  },
  {
    "LiveFrom": "01/01/2017",
    "CaseTypeID": "CARE_SUPERVISION_EPO",
    "CaseFieldID": "additionalApplicationsBundle",
    "ListElementCode": "c2DocumentBundle.supportingEvidenceLA",
    "AccessControl": [
      {
        "UserRoles": [
          "caseworker-publiclaw-courtadmin",
          "[CAFCASSSOLICITOR]",
          "[SOLICITOR]"
        ],
        "CRUD": "CU"
      },
      {
        "UserRoles": [
          "[LASOLICITOR]",
          "[LABARRISTER]"
        ],
        "CRUD": "CRU"
      },
      {
        "UserRoles": [
          "caseworker-publiclaw-cafcass"
        ],
        "CRUD": "R"
      },
      {
        "UserRoles": [
          "caseworker-publiclaw-gatekeeper",
          "caseworker-publiclaw-judiciary",
          "caseworker-publiclaw-magistrate",
          "[BARRISTER]"
        ],
        "CRUD": "U"
      }
    ]
  },
  {
    "LiveFrom": "01/01/2017",
    "CaseTypeID": "CARE_SUPERVISION_EPO",
    "CaseFieldID": "additionalApplicationsBundle",
    "ListElementCode": "c2DocumentBundle.supportingEvidenceNC",
    "AccessControl": [
      {
        "UserRoles": [
          "caseworker-publiclaw-courtadmin",
          "[LASOLICITOR]",
          "[LABARRISTER]"
        ],
        "CRUD": "CU"
      },
      {
        "UserRoles": [
          "caseworker-publiclaw-gatekeeper",
          "caseworker-publiclaw-judiciary",
          "caseworker-publiclaw-magistrate"
        ],
        "CRUD": "U"
      },
      {
        "UserRoles": [
          "[CAFCASSSOLICITOR]",
          "[SOLICITOR]"
        ],
        "CRUD": "CRU"
      },
      {
        "UserRoles": [
          "[BARRISTER]"
        ],
        "CRUD": "R"
      }
    ]
  },
  {
    "LiveFrom": "01/01/2017",
    "CaseTypeID": "CARE_SUPERVISION_EPO",
    "CaseFieldID": "additionalApplicationsBundle",
    "ListElementCode": "pbaPayment.usePbaPayment",
    "AccessControl": [
      {
        "UserRoles": [
          "[LABARRISTER]",
          "[SOLICITOR]",
          "[LASOLICITOR]",
          "[CAFCASSSOLICITOR]",
          "caseworker-publiclaw-courtadmin",
          "caseworker-publiclaw-cafcass"
        ],
        "CRUD": "CRU"
      },
      {
        "UserRoles": [
          "caseworker-publiclaw-gatekeeper",
          "caseworker-publiclaw-judiciary",
          "caseworker-publiclaw-magistrate",
          "[BARRISTER]"
        ],
        "CRUD": "R"
      }
    ]
  },
  {
    "LiveFrom": "01/01/2017",
    "CaseTypeID": "CARE_SUPERVISION_EPO",
    "CaseFieldID": "additionalApplicationsBundle",
    "ListElementCode": "pbaPayment.pbaNumber",
    "AccessControl": [
      {
        "UserRoles": [
          "[LABARRISTER]",
          "[SOLICITOR]",
          "[LASOLICITOR]",
          "[CAFCASSSOLICITOR]",
          "caseworker-publiclaw-courtadmin",
          "caseworker-publiclaw-cafcass"
        ],
        "CRUD": "CRU"
      },
      {
        "UserRoles": [
          "caseworker-publiclaw-gatekeeper",
          "caseworker-publiclaw-judiciary",
          "caseworker-publiclaw-magistrate",
          "[BARRISTER]"
        ],
        "CRUD": "R"
      }
    ]
  },
  {
    "LiveFrom": "01/01/2017",
    "CaseTypeID": "CARE_SUPERVISION_EPO",
    "CaseFieldID": "additionalApplicationsBundle",
    "ListElementCode": "pbaPayment.clientCode",
    "AccessControl": [
      {
        "UserRoles": [
          "[LABARRISTER]",
          "[SOLICITOR]",
          "[LASOLICITOR]",
          "[CAFCASSSOLICITOR]",
          "caseworker-publiclaw-courtadmin",
          "caseworker-publiclaw-cafcass"
        ],
        "CRUD": "CRU"
      },
      {
        "UserRoles": [
          "caseworker-publiclaw-gatekeeper",
          "caseworker-publiclaw-judiciary",
          "caseworker-publiclaw-magistrate",
          "[BARRISTER]"
        ],
        "CRUD": "R"
      }
    ]
  },
  {
    "LiveFrom": "01/01/2017",
    "CaseTypeID": "CARE_SUPERVISION_EPO",
    "CaseFieldID": "additionalApplicationsBundle",
    "ListElementCode": "pbaPayment.fileReference",
    "AccessControl": [
      {
        "UserRoles": [
          "[LABARRISTER]",
          "[SOLICITOR]",
          "[LASOLICITOR]",
          "[CAFCASSSOLICITOR]",
          "caseworker-publiclaw-courtadmin",
          "caseworker-publiclaw-cafcass"
        ],
        "CRUD": "CRU"
      },
      {
        "UserRoles": [
          "caseworker-publiclaw-gatekeeper",
          "caseworker-publiclaw-judiciary",
          "caseworker-publiclaw-magistrate",
          "[BARRISTER]"
        ],
        "CRUD": "R"
      }
    ]
  },
  {
    "LiveFrom": "01/01/2017",
    "CaseTypeID": "CARE_SUPERVISION_EPO",
    "CaseFieldID": "additionalApplicationsBundle",
    "ListElementCode": "otherApplicationsBundle.applicantName",
    "AccessControl": [
      {
        "UserRoles": [
          "[LABARRISTER]",
          "[SOLICITOR]",
          "[SOLICITORA]",
          "[SOLICITORB]",
          "[SOLICITORC]",
          "[SOLICITORD]",
          "[SOLICITORE]",
          "[SOLICITORF]",
          "[SOLICITORG]",
          "[SOLICITORH]",
          "[SOLICITORI]",
          "[SOLICITORJ]",
          "[CHILDSOLICITORA]",
          "[CHILDSOLICITORB]",
          "[CHILDSOLICITORC]",
          "[CHILDSOLICITORD]",
          "[CHILDSOLICITORE]",
          "[CHILDSOLICITORF]",
          "[CHILDSOLICITORG]",
          "[CHILDSOLICITORH]",
          "[CHILDSOLICITORI]",
          "[CHILDSOLICITORJ]",
          "[CHILDSOLICITORK]",
          "[CHILDSOLICITORL]",
          "[CHILDSOLICITORM]",
          "[CHILDSOLICITORN]",
          "[CHILDSOLICITORO]",
          "[LASOLICITOR]",
          "[CAFCASSSOLICITOR]",
          "caseworker-publiclaw-courtadmin",
          "caseworker-publiclaw-cafcass"
        ],
        "CRUD": "CRU"
      },
      {
        "UserRoles": [
          "caseworker-publiclaw-gatekeeper",
          "caseworker-publiclaw-judiciary",
          "caseworker-publiclaw-magistrate",
          "[BARRISTER]"
        ],
        "CRUD": "R"
      }
    ]
  },
  {
    "LiveFrom": "01/01/2017",
    "CaseTypeID": "CARE_SUPERVISION_EPO",
    "CaseFieldID": "additionalApplicationsBundle",
    "ListElementCode": "otherApplicationsBundle.document",
    "AccessControl": [
      {
        "UserRoles": [
          "[LABARRISTER]",
          "[SOLICITOR]",
          "[LASOLICITOR]",
          "[CAFCASSSOLICITOR]",
          "caseworker-publiclaw-courtadmin",
          "caseworker-publiclaw-cafcass"
        ],
        "CRUD": "CRU"
      },
      {
        "UserRoles": [
          "caseworker-publiclaw-gatekeeper",
          "caseworker-publiclaw-judiciary",
          "caseworker-publiclaw-magistrate",
          "[BARRISTER]"
        ],
        "CRUD": "R"
      }
    ]
  },
  {
    "LiveFrom": "01/01/2017",
    "CaseTypeID": "CARE_SUPERVISION_EPO",
    "CaseFieldID": "additionalApplicationsBundle",
    "ListElementCode": "otherApplicationsBundle.applicationType",
    "AccessControl": [
      {
        "UserRoles": [
          "[LABARRISTER]",
          "[SOLICITOR]",
          "[LASOLICITOR]",
          "[CAFCASSSOLICITOR]",
          "caseworker-publiclaw-courtadmin",
          "caseworker-publiclaw-cafcass"
        ],
        "CRUD": "CRU"
      },
      {
        "UserRoles": [
          "caseworker-publiclaw-gatekeeper",
          "caseworker-publiclaw-judiciary",
          "caseworker-publiclaw-magistrate",
          "[BARRISTER]"
        ],
        "CRUD": "R"
      }
    ]
  },
  {
    "LiveFrom": "01/01/2017",
    "CaseTypeID": "CARE_SUPERVISION_EPO",
    "CaseFieldID": "additionalApplicationsBundle",
    "ListElementCode": "otherApplicationsBundle.parentalResponsibilityType",
    "AccessControl": [
      {
        "UserRoles": [
          "[LABARRISTER]",
          "[SOLICITOR]",
          "[LASOLICITOR]",
          "[CAFCASSSOLICITOR]",
          "caseworker-publiclaw-courtadmin",
          "caseworker-publiclaw-cafcass"
        ],
        "CRUD": "CRU"
      },
      {
        "UserRoles": [
          "caseworker-publiclaw-gatekeeper",
          "caseworker-publiclaw-judiciary",
          "caseworker-publiclaw-magistrate",
          "[BARRISTER]"
        ],
        "CRUD": "R"
      }
    ]
  },
  {
    "LiveFrom": "01/01/2017",
    "CaseTypeID": "CARE_SUPERVISION_EPO",
    "CaseFieldID": "additionalApplicationsBundle",
    "ListElementCode": "otherApplicationsBundle.uploadedDateTime",
    "AccessControl": [
      {
        "UserRoles": [
          "[LABARRISTER]",
          "[SOLICITOR]",
          "[LASOLICITOR]",
          "[CAFCASSSOLICITOR]",
          "caseworker-publiclaw-courtadmin",
          "caseworker-publiclaw-cafcass"
        ],
        "CRUD": "CRU"
      },
      {
        "UserRoles": [
          "caseworker-publiclaw-gatekeeper",
          "caseworker-publiclaw-judiciary",
          "caseworker-publiclaw-magistrate",
          "[BARRISTER]"
        ],
        "CRUD": "R"
      }
    ]
  },
  {
    "LiveFrom": "01/01/2017",
    "CaseTypeID": "CARE_SUPERVISION_EPO",
    "CaseFieldID": "additionalApplicationsBundle",
    "ListElementCode": "otherApplicationsBundle.author",
    "AccessControl": [
      {
        "UserRoles": [
          "[LABARRISTER]",
          "[SOLICITOR]",
          "[LASOLICITOR]",
          "[CAFCASSSOLICITOR]",
          "caseworker-publiclaw-courtadmin",
          "caseworker-publiclaw-cafcass"
        ],
        "CRUD": "CRU"
      },
      {
        "UserRoles": [
          "caseworker-publiclaw-gatekeeper",
          "caseworker-publiclaw-judiciary",
          "caseworker-publiclaw-magistrate",
          "[BARRISTER]"
        ],
        "CRUD": "R"
      }
    ]
  },
  {
    "LiveFrom": "01/01/2017",
    "CaseTypeID": "CARE_SUPERVISION_EPO",
    "CaseFieldID": "additionalApplicationsBundle",
    "ListElementCode": "otherApplicationsBundle.supplementsBundle",
    "AccessControl": [
      {
        "UserRoles": [
          "[LABARRISTER]",
          "[SOLICITOR]",
          "[LASOLICITOR]",
          "[CAFCASSSOLICITOR]",
          "caseworker-publiclaw-courtadmin",
          "caseworker-publiclaw-cafcass"
        ],
        "CRUD": "CRU"
      },
      {
        "UserRoles": [
          "caseworker-publiclaw-gatekeeper",
          "caseworker-publiclaw-judiciary",
          "caseworker-publiclaw-magistrate",
          "[BARRISTER]"
        ],
        "CRUD": "R"
      }
    ]
  },
  {
    "LiveFrom": "01/01/2017",
    "CaseTypeID": "CARE_SUPERVISION_EPO",
    "CaseFieldID": "additionalApplicationsBundle",
    "ListElementCode": "otherApplicationsBundle.supportingEvidenceBundle",
    "AccessControl": [
      {
        "UserRoles": [
          "caseworker-publiclaw-courtadmin"
        ],
        "CRUD": "CRU"
      },
      {
        "UserRoles": [
          "[LASOLICITOR]",
          "[LABARRISTER]",
          "[CAFCASSSOLICITOR]",
          "[SOLICITOR]"
        ],
        "CRUD": "CU"
      },
      {
        "UserRoles": [
          "caseworker-publiclaw-gatekeeper",
          "caseworker-publiclaw-judiciary",
          "caseworker-publiclaw-magistrate"
        ],
        "CRUD": "R"
      },
      {
        "UserRoles": [
          "[BARRISTER]",
          "caseworker-publiclaw-cafcass"
        ],
        "CRUD": "U"
      }
    ]
  },
  {
    "LiveFrom": "01/01/2017",
    "CaseTypeID": "CARE_SUPERVISION_EPO",
    "CaseFieldID": "additionalApplicationsBundle",
    "ListElementCode": "otherApplicationsBundle.supportingEvidenceLA",
    "AccessControl": [
      {
        "UserRoles": [
          "caseworker-publiclaw-courtadmin",
          "[CAFCASSSOLICITOR]",
          "[SOLICITOR]"
        ],
        "CRUD": "CU"
      },
      {
        "UserRoles": [
          "[LASOLICITOR]",
          "[LABARRISTER]"
        ],
        "CRUD": "CRU"
      },
      {
        "UserRoles": [
          "caseworker-publiclaw-cafcass"
        ],
        "CRUD": "R"
      },
      {
        "UserRoles": [
          "caseworker-publiclaw-gatekeeper",
          "caseworker-publiclaw-judiciary",
          "caseworker-publiclaw-magistrate",
          "[BARRISTER]"
        ],
        "CRUD": "U"
      }
    ]
  },
  {
    "LiveFrom": "01/01/2017",
    "CaseTypeID": "CARE_SUPERVISION_EPO",
    "CaseFieldID": "additionalApplicationsBundle",
    "ListElementCode": "otherApplicationsBundle.supportingEvidenceNC",
    "AccessControl": [
      {
        "UserRoles": [
          "caseworker-publiclaw-courtadmin",
          "[LASOLICITOR]",
          "[LABARRISTER]"
        ],
        "CRUD": "CU"
      },
      {
        "UserRoles": [
          "caseworker-publiclaw-gatekeeper",
          "caseworker-publiclaw-judiciary",
          "caseworker-publiclaw-magistrate"
        ],
        "CRUD": "U"
      },
      {
        "UserRoles": [
          "[CAFCASSSOLICITOR]",
          "[SOLICITOR]"
        ],
        "CRUD": "CRU"
      },
      {
        "UserRoles": [
          "[BARRISTER]"
        ],
        "CRUD": "R"
      }
    ]
  },
  {
    "LiveFrom": "01/01/2017",
    "CaseTypeID": "CARE_SUPERVISION_EPO",
    "CaseFieldID": "additionalApplicationsBundle",
    "ListElementCode": "otherApplicationsBundle.id",
    "AccessControl": [
      {
        "UserRoles": [
          "[LABARRISTER]",
          "[SOLICITOR]",
          "[LASOLICITOR]",
          "[CAFCASSSOLICITOR]",
          "caseworker-publiclaw-courtadmin",
          "caseworker-publiclaw-cafcass"
        ],
        "CRUD": "CRU"
      },
      {
        "UserRoles": [
          "caseworker-publiclaw-gatekeeper",
          "caseworker-publiclaw-judiciary",
          "caseworker-publiclaw-magistrate",
          "[BARRISTER]"
        ],
        "CRUD": "R"
      }
    ]
  },
  {
    "LiveFrom": "01/01/2017",
    "CaseTypeID": "CARE_SUPERVISION_EPO",
    "CaseFieldID": "additionalApplicationsBundle",
    "ListElementCode": "c2DocumentBundle.id",
    "AccessControl": [
      {
        "UserRoles": [
          "[LABARRISTER]",
          "[SOLICITOR]",
          "[LASOLICITOR]",
          "[CAFCASSSOLICITOR]",
          "caseworker-publiclaw-courtadmin",
          "caseworker-publiclaw-cafcass"
        ],
        "CRUD": "CRU"
      },
      {
        "UserRoles": [
          "caseworker-publiclaw-gatekeeper",
          "caseworker-publiclaw-judiciary",
          "caseworker-publiclaw-magistrate",
          "[BARRISTER]"
        ],
        "CRUD": "R"
      }
    ]
  },
  {
    "LiveFrom": "01/01/2017",
    "CaseTypeID": "CARE_SUPERVISION_EPO",
    "CaseFieldID": "additionalApplicationsBundle",
    "ListElementCode": "c2DocumentBundle.supplementsBundle",
    "AccessControl": [
      {
        "UserRoles": [
          "[LABARRISTER]",
          "[SOLICITOR]",
          "[LASOLICITOR]",
          "[CAFCASSSOLICITOR]",
          "caseworker-publiclaw-courtadmin",
          "caseworker-publiclaw-cafcass"
        ],
        "CRUD": "CRU"
      },
      {
        "UserRoles": [
          "caseworker-publiclaw-gatekeeper",
          "caseworker-publiclaw-judiciary",
          "caseworker-publiclaw-magistrate",
          "[BARRISTER]"
        ],
        "CRUD": "R"
      }
    ]
  },
  {
    "LiveFrom": "01/01/2017",
    "CaseTypeID": "CARE_SUPERVISION_EPO",
    "CaseFieldID": "additionalApplicationsBundle",
    "ListElementCode": "c2DocumentBundle.c2AdditionalOrdersRequested",
    "AccessControl": [
      {
        "UserRoles": [
          "[LABARRISTER]",
          "[SOLICITOR]",
          "[LASOLICITOR]",
          "[CAFCASSSOLICITOR]",
          "caseworker-publiclaw-courtadmin",
          "caseworker-publiclaw-cafcass"
        ],
        "CRUD": "CRU"
      },
      {
        "UserRoles": [
          "caseworker-publiclaw-gatekeeper",
          "caseworker-publiclaw-judiciary",
          "caseworker-publiclaw-magistrate",
          "[BARRISTER]"
        ],
        "CRUD": "R"
      }
    ]
  },
  {
    "LiveFrom": "01/01/2017",
    "CaseTypeID": "CARE_SUPERVISION_EPO",
    "CaseFieldID": "additionalApplicationsBundle",
    "ListElementCode": "c2DocumentBundle.parentalResponsibilityType",
    "AccessControl": [
      {
        "UserRoles": [
          "[LABARRISTER]",
          "[SOLICITOR]",
          "[LASOLICITOR]",
          "[CAFCASSSOLICITOR]",
          "caseworker-publiclaw-courtadmin",
          "caseworker-publiclaw-cafcass"
        ],
        "CRUD": "CRU"
      },
      {
        "UserRoles": [
          "caseworker-publiclaw-gatekeeper",
          "caseworker-publiclaw-judiciary",
          "caseworker-publiclaw-magistrate",
          "[BARRISTER]"
        ],
        "CRUD": "R"
      }
    ]
  },
  {
    "LiveFrom": "01/01/2017",
    "CaseTypeID": "CARE_SUPERVISION_EPO",
    "CaseFieldID": "additionalApplicationsBundle",
    "ListElementCode": "c2DocumentBundle.othersNotified",
    "AccessControl": [
      {
        "UserRoles": [
          "[LABARRISTER]",
          "[SOLICITOR]",
          "[SOLICITORA]",
          "[SOLICITORB]",
          "[SOLICITORC]",
          "[SOLICITORD]",
          "[SOLICITORE]",
          "[SOLICITORF]",
          "[SOLICITORG]",
          "[SOLICITORH]",
          "[SOLICITORI]",
          "[SOLICITORJ]",
          "[LASOLICITOR]",
          "[CAFCASSSOLICITOR]",
          "caseworker-publiclaw-courtadmin",
          "caseworker-publiclaw-cafcass"
        ],
        "CRUD": "CRU"
      },
      {
        "UserRoles": [
          "caseworker-publiclaw-gatekeeper",
          "caseworker-publiclaw-judiciary",
          "caseworker-publiclaw-magistrate",
          "[BARRISTER]"
        ],
        "CRUD": "R"
      }
    ]
  },
  {
    "LiveFrom": "01/01/2017",
    "CaseTypeID": "CARE_SUPERVISION_EPO",
    "CaseFieldID": "additionalApplicationsBundle",
    "ListElementCode": "c2DocumentBundle.others",
    "AccessControl": [
      {
        "UserRoles": [
          "[LABARRISTER]",
          "[SOLICITOR]",
          "[SOLICITORA]",
          "[SOLICITORB]",
          "[SOLICITORC]",
          "[SOLICITORD]",
          "[SOLICITORE]",
          "[SOLICITORF]",
          "[SOLICITORG]",
          "[SOLICITORH]",
          "[SOLICITORI]",
          "[SOLICITORJ]",
          "[LASOLICITOR]",
          "[CAFCASSSOLICITOR]",
          "caseworker-publiclaw-courtadmin",
          "caseworker-publiclaw-cafcass"
        ],
        "CRUD": "CRU"
      },
      {
        "UserRoles": [
          "caseworker-publiclaw-gatekeeper",
          "caseworker-publiclaw-judiciary",
          "caseworker-publiclaw-magistrate",
          "[BARRISTER]"
        ],
        "CRUD": "R"
      }
    ]
  },
  {
    "LiveFrom": "01/01/2017",
    "CaseTypeID": "CARE_SUPERVISION_EPO",
    "CaseFieldID": "additionalApplicationsBundle",
    "ListElementCode": "c2DocumentBundle.respondents",
    "AccessControl": [
      {
        "UserRoles": [
          "[LABARRISTER]",
          "[SOLICITOR]",
          "[SOLICITORA]",
          "[SOLICITORB]",
          "[SOLICITORC]",
          "[SOLICITORD]",
          "[SOLICITORE]",
          "[SOLICITORF]",
          "[SOLICITORG]",
          "[SOLICITORH]",
          "[SOLICITORI]",
          "[SOLICITORJ]",
          "[LASOLICITOR]",
          "[CAFCASSSOLICITOR]",
          "caseworker-publiclaw-courtadmin",
          "caseworker-publiclaw-cafcass"
        ],
        "CRUD": "CRU"
      },
      {
        "UserRoles": [
          "caseworker-publiclaw-gatekeeper",
          "caseworker-publiclaw-judiciary",
          "caseworker-publiclaw-magistrate",
          "[BARRISTER]"
        ],
        "CRUD": "R"
      }
    ]
  },
  {
    "LiveFrom": "01/01/2017",
    "CaseTypeID": "CARE_SUPERVISION_EPO",
    "CaseFieldID": "additionalApplicationsBundle",
    "ListElementCode": "otherApplicationsBundle.othersNotified",
    "AccessControl": [
      {
        "UserRoles": [
          "[LABARRISTER]",
          "[SOLICITOR]",
          "[SOLICITORA]",
          "[SOLICITORB]",
          "[SOLICITORC]",
          "[SOLICITORD]",
          "[SOLICITORE]",
          "[SOLICITORF]",
          "[SOLICITORG]",
          "[SOLICITORH]",
          "[SOLICITORI]",
          "[SOLICITORJ]",
          "[LASOLICITOR]",
          "[CAFCASSSOLICITOR]",
          "caseworker-publiclaw-courtadmin",
          "caseworker-publiclaw-cafcass"
        ],
        "CRUD": "CRU"
      },
      {
        "UserRoles": [
          "caseworker-publiclaw-gatekeeper",
          "caseworker-publiclaw-judiciary",
          "caseworker-publiclaw-magistrate",
          "[BARRISTER]"
        ],
        "CRUD": "R"
      }
    ]
  },
  {
    "LiveFrom": "01/01/2017",
    "CaseTypeID": "CARE_SUPERVISION_EPO",
    "CaseFieldID": "additionalApplicationsBundle",
    "ListElementCode": "otherApplicationsBundle.others",
    "AccessControl": [
      {
        "UserRoles": [
          "[LABARRISTER]",
          "[SOLICITOR]",
          "[SOLICITORA]",
          "[SOLICITORB]",
          "[SOLICITORC]",
          "[SOLICITORD]",
          "[SOLICITORE]",
          "[SOLICITORF]",
          "[SOLICITORG]",
          "[SOLICITORH]",
          "[SOLICITORI]",
          "[SOLICITORJ]",
          "[LASOLICITOR]",
          "[CAFCASSSOLICITOR]",
          "caseworker-publiclaw-courtadmin",
          "caseworker-publiclaw-cafcass"
        ],
        "CRUD": "CRU"
      },
      {
        "UserRoles": [
          "caseworker-publiclaw-gatekeeper",
          "caseworker-publiclaw-judiciary",
          "caseworker-publiclaw-magistrate",
          "[BARRISTER]"
        ],
        "CRUD": "R"
      }
    ]
  },
  {
    "LiveFrom": "01/01/2017",
    "CaseTypeID": "CARE_SUPERVISION_EPO",
    "CaseFieldID": "additionalApplicationsBundle",
    "ListElementCode": "otherApplicationsBundle.respondents",
    "AccessControl": [
      {
        "UserRoles": [
          "[LABARRISTER]",
          "[SOLICITOR]",
          "[SOLICITORA]",
          "[SOLICITORB]",
          "[SOLICITORC]",
          "[SOLICITORD]",
          "[SOLICITORE]",
          "[SOLICITORF]",
          "[SOLICITORG]",
          "[SOLICITORH]",
          "[SOLICITORI]",
          "[SOLICITORJ]",
          "[LASOLICITOR]",
          "[CAFCASSSOLICITOR]",
          "caseworker-publiclaw-courtadmin",
          "caseworker-publiclaw-cafcass"
        ],
        "CRUD": "CRU"
      },
      {
        "UserRoles": [
          "caseworker-publiclaw-gatekeeper",
          "caseworker-publiclaw-judiciary",
          "caseworker-publiclaw-magistrate",
          "[BARRISTER]"
        ],
        "CRUD": "R"
      }
    ]
  }
]
