[
  {
    "LiveFrom": "01/01/2017",
    "ID": "ListGatekeepingHearingTypeList",
    "ListElementCode": "EMERGENCY_PROTECTION_ORDER",
    "ListElement": "Emergency protection order",
    "DisplayOrder": 1
  },
  {
    "LiveFrom": "01/01/2017",
    "ID": "ListGatekeepingHearingTypeList",
    "ListElementCode": "INTERIM_CARE_ORDER",
    "ListElement": "Interim care order",
    "DisplayOrder": 2
  },
  {
    "LiveFrom": "01/01/2017",
    "ID": "ListGatekeepingHearingTypeList",
    "ListElementCode": "CASE_MANAGEMENT",
    "ListElement": "Case management",
    "DisplayOrder": 3
  },
  {
    "LiveFrom": "01/01/2017",
    "ID": "ListGatekeepingHearingTypeList",
    "ListElementCode": "FURTHER_CASE_MANAGEMENT",
    "ListElement": "Further case management",
    "DisplayOrder": 4
  },
  {
    "LiveFrom": "01/01/2017",
    "ID": "ListGatekeepingHearingTypeList",
    "ListElementCode": "FACT_FINDING",
    "ListElement": "Fact finding",
    "DisplayOrder": 5
  },
  {
    "LiveFrom": "01/01/2017",
    "ID": "ListGatekeepingHearingTypeList",
    "ListElementCode": "ISSUE_RESOLUTION",
    "ListElement": "Issue resolution",
    "DisplayOrder": 6
  },
  {
    "LiveFrom": "01/01/2017",
    "ID": "ListGatekeepingHearingTypeList",
    "ListElementCode": "FINAL",
    "ListElement": "Full hearing",
    "DisplayOrder": 7
  },
  {
    "LiveFrom": "01/01/2017",
    "ID": "ListGatekeepingHearingTypeList",
    "ListElementCode": "JUDGMENT_AFTER_HEARING",
    "ListElement": "Judgment after hearing",
    "DisplayOrder": 8
  },
  {
    "LiveFrom": "01/01/2017",
    "ID": "ListGatekeepingHearingTypeList",
    "ListElementCode": "ACCELERATED_DISCHARGE_OF_CARE",
    "ListElement": "Discharge of care",
    "DisplayOrder": 9
  },
  {
    "LiveFrom": "01/01/2017",
    "ID": "ListGatekeepingHearingTypeList",
    "ListElementCode": "FAMILY_DRUG_ALCOHOL_COURT",
    "ListElement": "Family drug & alcohol court",
    "DisplayOrder": 10
  }
]