[
  {
    "LiveFrom": "01/01/2017",
    "ID": "JudicialMessageMetaData",
    "CaseEventID": "messageJudgeOrLegalAdviser",
    "CaseFieldID": "judicialMessageReply",
    "ListElementCode": "recipient",
    "FieldDisplayOrder": 1,
    "DisplayContext": "READONLY"
  },
  {
    "LiveFrom": "01/01/2017",
    "ID": "JudicialMessageMetaData",
    "CaseEventID": "messageJudgeOrLegalAdviser",
    "CaseFieldID": "judicialMessageReply",
    "ListElementCode": "sender",
    "SecurityClassification": "Public",
    "FieldDisplayOrder": 2,
    "DisplayContext": "READONLY"
  },
  {
    "LiveFrom": "01/01/2017",
    "ID": "JudicialMessageMetaData",
    "CaseEventID": "messageJudgeOrLegalAdviser",
    "CaseFieldID": "judicialMessageReply",
    "ListElementCode": "urgency",
    "FieldDisplayOrder": 3,
    "DisplayContext": "READONLY"
  },
  {
    "LiveFrom": "01/01/2017",
    "ID": "JudicialMessageMetaData",
    "CaseEventID": "messageJudgeOrLegalAdviser",
    "CaseFieldID": "judicialMessageReply",
    "ListElementCode": "note",
    "FieldDisplayOrder": 4,
    "DisplayContext": "READONLY"
  }
]
